README.md
setup.cfg
setup.py
log_correlation_asgi/__init__.py
log_correlation_asgi/filter.py
log_correlation_asgi/middleware.py
log_correlation_asgi.egg-info/PKG-INFO
log_correlation_asgi.egg-info/SOURCES.txt
log_correlation_asgi.egg-info/dependency_links.txt
log_correlation_asgi.egg-info/top_level.txt