Metadata-Version: 2.1
Name: log-correlation-asgi
Version: 0.1.0
Summary: Log correlation middleware and filters for ASGI frameworks.
Home-page: https://github.com/shaihulud/log-correlation-asgi
Author: Denis Zalivin
Author-email: zalivindenis@gmail.com
License: MIT
Platform: UNKNOWN
Classifier: Development Status :: 3 - Alpha
Classifier: Environment :: Web Environment
Classifier: Intended Audience :: Developers
Classifier: License :: OSI Approved :: MIT License
Classifier: Operating System :: OS Independent
Classifier: Topic :: Internet :: WWW/HTTP
Classifier: Programming Language :: Python :: 3
Requires-Python: >=3.6
